spyndex/__init__.py
spyndex/axioms.py
spyndex/datasets.py
spyndex/plot.py
spyndex/spyndex.py
spyndex/utils.py
spyndex/data/S2_10m.json
spyndex/data/__init__.py
spyndex/data/bands.json
spyndex/data/constants.json
spyndex/data/spectral-indices-dict.json
spyndex/data/spectral.json
spyndex-0.9.0.dist-info/licenses/LICENSE
spyndex-0.9.0.dist-info/METADATA
spyndex-0.9.0.dist-info/WHEEL
spyndex-0.9.0.dist-info/top_level.txt
spyndex-0.9.0.dist-info/RECORD
