Metadata-Version: 2.4
Name: spyndex
Version: 0.9.0
Summary: Awesome Spectral Indices in Python
Author-email: David Montero Loaiza <dml.mont@gmail.com>
Project-URL: Bug Tracker, https://github.com/awesome-spectral-indices/spyndex/issues
Project-URL: Documentation, https://spyndex.readthedocs.io
Project-URL: Source Code, https://github.com/awesome-spectral-indices/spyndex
Classifier: Development Status :: 2 - Pre-Alpha
Classifier: License :: OSI Approved :: MIT License
Classifier: Programming Language :: Python
Classifier: Programming Language :: Python :: 3
Classifier: Programming Language :: Python :: 3.8
Classifier: Programming Language :: Python :: 3.9
Requires-Python: >=3.8
License-File: LICENSE
Requires-Dist: dask>=2023.7.0
Requires-Dist: matplotlib
Requires-Dist: pandas>=2.0.3
Requires-Dist: pyarrow
Requires-Dist: python-box>=6.0
Requires-Dist: requests
Requires-Dist: seaborn
Requires-Dist: xarray>=2023.6.0
Provides-Extra: ee
Requires-Dist: earthengine-api>=1.5.24; extra == "ee"
Requires-Dist: eemont>=2025.7.1; extra == "ee"
Dynamic: license-file
